[
  {
    "name": "accordion",
    "dependencies": [
      "@radix-ui/react-accordion"
    ],
    "files": [
      "ui/accordion.tsx"
    ],
    "type": "components:ui"
  },
  {
    "name": "alert",
    "files": [
      "ui/alert.tsx"
    ],
    "type": "components:ui"
  },
  {
    "name": "alert-dialog",
    "dependencies": [
      "@radix-ui/react-alert-dialog"
    ],
    "registryDependencies": [
      "button"
    ],
    "files": [
      "ui/alert-dialog.tsx"
    ],
    "type": "components:ui"
  },
  {
    "name": "animated-beam",
    "files": [
      "ui/animated-beam.tsx"
    ],
    "type": "components:ui"
  },
  {
    "name": "animated-grid-pattern",
    "files": [
      "ui/animated-grid-pattern.tsx"
    ],
    "type": "components:ui"
  },
  {
    "name": "animated-lines",
    "files": [
      "ui/animated-lines.tsx"
    ],
    "type": "components:ui"
  },
  {
    "name": "animated-list",
    "files": [
      "ui/animated-list.tsx"
    ],
    "type": "components:ui"
  },
  {
    "name": "animated-shiny-text",
    "files": [
      "ui/animated-shiny-text.tsx"
    ],
    "type": "components:ui"
  },
  {
    "name": "animated-subscribe-button",
    "files": [
      "ui/animated-subscribe-button.tsx"
    ],
    "type": "components:ui"
  },
  {
    "name": "animated-gradient-text",
    "files": [
      "ui/animated-gradient-text.tsx"
    ],
    "type": "components:ui"
  },
  {
    "name": "aspect-ratio",
    "dependencies": [
      "@radix-ui/react-aspect-ratio"
    ],
    "files": [
      "ui/aspect-ratio.tsx"
    ],
    "type": "components:ui"
  },
  {
    "name": "avatar",
    "dependencies": [
      "@radix-ui/react-avatar"
    ],
    "files": [
      "ui/avatar.tsx"
    ],
    "type": "components:ui"
  },
  {
    "name": "avatar-circles",
    "files": [
      "ui/avatar-circles.tsx"
    ],
    "type": "components:ui"
  },
  {
    "name": "badge",
    "files": [
      "ui/badge.tsx"
    ],
    "type": "components:ui"
  },
  {
    "name": "bento-grid",
    "dependencies": [
      "@radix-ui/react-icons"
    ],
    "registryDependencies": [
      "button"
    ],
    "files": [
      "ui/bento-grid.tsx"
    ],
    "type": "components:ui"
  },
  {
    "name": "blur-in",
    "files": [
      "ui/blur-in.tsx"
    ],
    "type": "components:ui"
  },
  {
    "name": "border-beam",
    "files": [
      "ui/border-beam.tsx"
    ],
    "type": "components:ui"
  },
  {
    "name": "box-reveal",
    "files": [
      "ui/box-reveal.tsx"
    ],
    "type": "components:ui"
  },
  {
    "name": "breadcrumb",
    "dependencies": [
      "@radix-ui/react-slot"
    ],
    "files": [
      "ui/breadcrumb.tsx"
    ],
    "type": "components:ui"
  },
  {
    "name": "button",
    "dependencies": [
      "@radix-ui/react-slot"
    ],
    "files": [
      "ui/button.tsx"
    ],
    "type": "components:ui"
  },
  {
    "name": "blur-fade",
    "files": [
      "ui/blur-fade.tsx"
    ],
    "type": "components:ui"
  },
  {
    "name": "calendar",
    "dependencies": [
      "react-day-picker",
      "date-fns"
    ],
    "registryDependencies": [
      "button"
    ],
    "files": [
      "ui/calendar.tsx"
    ],
    "type": "components:ui"
  },
  {
    "name": "card",
    "files": [
      "ui/card.tsx"
    ],
    "type": "components:ui"
  },
  {
    "name": "carousel",
    "dependencies": [
      "embla-carousel-react"
    ],
    "registryDependencies": [
      "button"
    ],
    "files": [
      "ui/carousel.tsx"
    ],
    "type": "components:ui"
  },
  {
    "name": "chart",
    "dependencies": [
      "recharts"
    ],
    "files": [
      "ui/chart.tsx"
    ],
    "type": "components:ui"
  },
  {
    "name": "checkbox",
    "dependencies": [
      "@radix-ui/react-checkbox"
    ],
    "files": [
      "ui/checkbox.tsx"
    ],
    "type": "components:ui"
  },
  {
    "name": "client-tweet-card",
    "files": [
      "ui/client-tweet-card.tsx"
    ],
    "type": "components:ui"
  },
  {
    "name": "collapsible",
    "dependencies": [
      "@radix-ui/react-collapsible"
    ],
    "files": [
      "ui/collapsible.tsx"
    ],
    "type": "components:ui"
  },
  {
    "name": "command",
    "dependencies": [
      "cmdk"
    ],
    "registryDependencies": [
      "dialog"
    ],
    "files": [
      "ui/command.tsx"
    ],
    "type": "components:ui"
  },
  {
    "name": "confetti",
    "dependencies": [
      "canvas-confetti"
    ],
    "files": [
      "ui/confetti.tsx"
    ],
    "type": "components:ui"
  },
  {
    "name": "context-menu",
    "dependencies": [
      "@radix-ui/react-context-menu"
    ],
    "files": [
      "ui/context-menu.tsx"
    ],
    "type": "components:ui"
  },
  {
    "name": "cool-mode",
    "files": [
      "ui/cool-mode.tsx"
    ],
    "type": "components:ui"
  },
  {
    "name": "dialog",
    "dependencies": [
      "@radix-ui/react-dialog"
    ],
    "files": [
      "ui/dialog.tsx"
    ],
    "type": "components:ui"
  },
  {
    "name": "dock",
    "files": [
      "ui/dock.tsx"
    ],
    "type": "components:ui"
  },
  {
    "name": "dot-pattern",
    "files": [
      "ui/dot-pattern.tsx"
    ],
    "type": "components:ui"
  },
  {
    "name": "drawer",
    "dependencies": [
      "vaul",
      "@radix-ui/react-dialog"
    ],
    "files": [
      "ui/drawer.tsx"
    ],
    "type": "components:ui"
  },
  {
    "name": "dropdown-menu",
    "dependencies": [
      "@radix-ui/react-dropdown-menu"
    ],
    "files": [
      "ui/dropdown-menu.tsx"
    ],
    "type": "components:ui"
  },
  {
    "name": "fade-text",
    "files": [
      "ui/fade-text.tsx"
    ],
    "type": "components:ui"
  },
  {
    "name": "file-tree",
    "files": [
      "ui/file-tree.tsx"
    ],
    "type": "components:ui"
  },
  {
    "name": "flip-text",
    "files": [
      "ui/flip-text.tsx"
    ],
    "type": "components:ui"
  },
  {
    "name": "form",
    "dependencies": [
      "@radix-ui/react-label",
      "@radix-ui/react-slot",
      "@hookform/resolvers",
      "zod",
      "react-hook-form"
    ],
    "registryDependencies": [
      "button",
      "label"
    ],
    "files": [
      "ui/form.tsx"
    ],
    "type": "components:ui"
  },
  {
    "name": "globe",
    "dependencies": [
      "react-spring"
    ],
    "files": [
      "ui/globe.tsx"
    ],
    "type": "components:ui"
  },
  {
    "name": "gradual-spacing",
    "files": [
      "ui/gradual-spacing.tsx"
    ],
    "type": "components:ui"
  },
  {
    "name": "grid-pattern",
    "files": [
      "ui/grid-pattern.tsx"
    ],
    "type": "components:ui"
  },
  {
    "name": "gauge-circle",
    "files": [
      "ui/gauge-circle.tsx"
    ],
    "type": "components:ui"
  },
  {
    "name": "hero-video",
    "files": [
      "ui/hero-video.tsx"
    ],
    "type": "components:ui"
  },
  {
    "name": "hover-card",
    "dependencies": [
      "@radix-ui/react-hover-card"
    ],
    "files": [
      "ui/hover-card.tsx"
    ],
    "type": "components:ui"
  },
  {
    "name": "icon-cloud",
    "dependencies": [
      "react-icon-cloud"
    ],
    "files": [
      "ui/icon-cloud.tsx"
    ],
    "type": "components:ui"
  },
  {
    "name": "input",
    "files": [
      "ui/input.tsx"
    ],
    "type": "components:ui"
  },
  {
    "name": "input-otp",
    "dependencies": [
      "input-otp"
    ],
    "files": [
      "ui/input-otp.tsx"
    ],
    "type": "components:ui"
  },
  {
    "name": "input-phone",
    "dependencies": [
      "react-phone-number-input"
    ],
    "registryDependencies": [
      "button",
      "input",
      "popover"
    ],
    "files": [
      "ui/input-phone.tsx"
    ],
    "type": "components:ui"
  },
  {
    "name": "label",
    "dependencies": [
      "@radix-ui/react-label"
    ],
    "files": [
      "ui/label.tsx"
    ],
    "type": "components:ui"
  },
  {
    "name": "letter-pullup",
    "files": [
      "ui/letter-pullup.tsx"
    ],
    "type": "components:ui"
  },
  {
    "name": "linear-gradient",
    "files": [
      "ui/linear-gradient.tsx"
    ],
    "type": "components:ui"
  },
  {
    "name": "magic-card",
    "files": [
      "ui/magic-card.tsx"
    ],
    "type": "components:ui"
  },
  {
    "name": "marquee",
    "files": [
      "ui/marquee.tsx"
    ],
    "type": "components:ui"
  },
  {
    "name": "menubar",
    "dependencies": [
      "@radix-ui/react-menubar"
    ],
    "files": [
      "ui/menubar.tsx"
    ],
    "type": "components:ui"
  },
  {
    "name": "meteors",
    "files": [
      "ui/meteors.tsx"
    ],
    "type": "components:ui"
  },
  {
    "name": "multi-select",
    "files": [
      "ui/multi-select.tsx"
    ],
    "type": "components:ui"
  },
  {
    "name": "navigation-menu",
    "dependencies": [
      "@radix-ui/react-navigation-menu"
    ],
    "files": [
      "ui/navigation-menu.tsx"
    ],
    "type": "components:ui"
  },
  {
    "name": "neon-gradient-card",
    "files": [
      "ui/neon-gradient-card.tsx"
    ],
    "type": "components:ui"
  },
  {
    "name": "number-ticker",
    "files": [
      "ui/number-ticker.tsx"
    ],
    "type": "components:ui"
  },
  {
    "name": "orbiting-circles",
    "files": [
      "ui/orbiting-circles.tsx"
    ],
    "type": "components:ui"
  },
  {
    "name": "pagination",
    "registryDependencies": [
      "button"
    ],
    "files": [
      "ui/pagination.tsx"
    ],
    "type": "components:ui"
  },
  {
    "name": "particles",
    "files": [
      "ui/particles.tsx"
    ],
    "type": "components:ui"
  },
  {
    "name": "popover",
    "dependencies": [
      "@radix-ui/react-popover"
    ],
    "files": [
      "ui/popover.tsx"
    ],
    "type": "components:ui"
  },
  {
    "name": "progress",
    "dependencies": [
      "@radix-ui/react-progress"
    ],
    "files": [
      "ui/progress.tsx"
    ],
    "type": "components:ui"
  },
  {
    "name": "pulsating-button",
    "files": [
      "ui/pulsating-button.tsx"
    ],
    "type": "components:ui"
  },
  {
    "name": "radio-group",
    "dependencies": [
      "@radix-ui/react-radio-group"
    ],
    "files": [
      "ui/radio-group.tsx"
    ],
    "type": "components:ui"
  },
  {
    "name": "radial-gradient",
    "files": [
      "ui/radial-gradient.tsx"
    ],
    "type": "components:ui"
  },
  {
    "name": "resizable",
    "dependencies": [
      "react-resizable-panels"
    ],
    "files": [
      "ui/resizable.tsx"
    ],
    "type": "components:ui"
  },
  {
    "name": "retro-grid",
    "files": [
      "ui/retro-grid.tsx"
    ],
    "type": "components:ui"
  },
  {
    "name": "ripple",
    "files": [
      "ui/ripple.tsx"
    ],
    "type": "components:ui"
  },
  {
    "name": "scroll-area",
    "dependencies": [
      "@radix-ui/react-scroll-area"
    ],
    "files": [
      "ui/scroll-area.tsx"
    ],
    "type": "components:ui"
  },
  {
    "name": "scroll-based-velocity",
    "dependencies": [
      "@motionone/utils"
    ],
    "files": [
      "ui/scroll-based-velocity.tsx"
    ],
    "type": "components:ui"
  },
  {
    "name": "scroll-progress",
    "files": [
      "ui/scroll-progress.tsx"
    ],
    "type": "components:ui"
  },
  {
    "name": "select",
    "dependencies": [
      "@radix-ui/react-select"
    ],
    "files": [
      "ui/select.tsx"
    ],
    "type": "components:ui"
  },
  {
    "name": "separate-away",
    "files": [
      "ui/separate-away.tsx"
    ],
    "type": "components:ui"
  },
  {
    "name": "separator",
    "dependencies": [
      "@radix-ui/react-separator"
    ],
    "files": [
      "ui/separator.tsx"
    ],
    "type": "components:ui"
  },
  {
    "name": "sheet",
    "dependencies": [
      "@radix-ui/react-dialog"
    ],
    "files": [
      "ui/sheet.tsx"
    ],
    "type": "components:ui"
  },
  {
    "name": "shimmer-button",
    "files": [
      "ui/shimmer-button.tsx"
    ],
    "type": "components:ui"
  },
  {
    "name": "shine-border",
    "files": [
      "ui/shine-border.tsx"
    ],
    "type": "components:ui"
  },
  {
    "name": "shiny-button",
    "files": [
      "ui/shiny-button.tsx"
    ],
    "type": "components:ui"
  },
  {
    "name": "skeleton",
    "files": [
      "ui/skeleton.tsx"
    ],
    "type": "components:ui"
  },
  {
    "name": "slider",
    "dependencies": [
      "@radix-ui/react-slider"
    ],
    "files": [
      "ui/slider.tsx"
    ],
    "type": "components:ui"
  },
  {
    "name": "sonner",
    "dependencies": [
      "sonner",
      "next-themes"
    ],
    "files": [
      "ui/sonner.tsx"
    ],
    "type": "components:ui"
  },
  {
    "name": "sparkles-text",
    "files": [
      "ui/sparkles-text.tsx"
    ],
    "type": "components:ui"
  },
  {
    "name": "star-rating",
    "files": [
      "ui/star-rating.tsx"
    ],
    "type": "components:ui"
  },
  {
    "name": "switch",
    "dependencies": [
      "@radix-ui/react-switch"
    ],
    "files": [
      "ui/switch.tsx"
    ],
    "type": "components:ui"
  },
  {
    "name": "stepper",
    "files": [
      "ui/stepper.tsx"
    ],
    "type": "components:ui"
  },
  {
    "name": "scratch-to-reveal",
    "files": [
      "ui/scratch-to-reveal.tsx"
    ],
    "type": "components:ui"
  },
  {
    "name": "table",
    "files": [
      "ui/table.tsx"
    ],
    "type": "components:ui"
  },
  {
    "name": "tabs",
    "dependencies": [
      "@radix-ui/react-tabs"
    ],
    "files": [
      "ui/tabs.tsx"
    ],
    "type": "components:ui"
  },
  {
    "name": "textarea",
    "files": [
      "ui/textarea.tsx"
    ],
    "type": "components:ui"
  },
  {
    "name": "text-reveal",
    "files": [
      "ui/text-reveal.tsx"
    ],
    "type": "components:ui"
  },
  {
    "name": "timeline",
    "files": [
      "ui/timeline.tsx"
    ],
    "type": "components:ui"
  },
  {
    "name": "toc",
    "files": [
      "ui/toc.tsx"
    ],
    "type": "components:ui"
  },
  {
    "name": "toast",
    "dependencies": [
      "@radix-ui/react-toast"
    ],
    "files": [
      "ui/toast.tsx",
      "ui/use-toast.ts",
      "ui/toaster.tsx"
    ],
    "type": "components:ui"
  },
  {
    "name": "toggle",
    "dependencies": [
      "@radix-ui/react-toggle"
    ],
    "files": [
      "ui/toggle.tsx"
    ],
    "type": "components:ui"
  },
  {
    "name": "toggle-group",
    "dependencies": [
      "@radix-ui/react-toggle-group"
    ],
    "registryDependencies": [
      "toggle"
    ],
    "files": [
      "ui/toggle-group.tsx"
    ],
    "type": "components:ui"
  },
  {
    "name": "tooltip",
    "dependencies": [
      "@radix-ui/react-tooltip"
    ],
    "files": [
      "ui/tooltip.tsx"
    ],
    "type": "components:ui"
  },
  {
    "name": "tour",
    "files": [
      "ui/tour.tsx"
    ],
    "type": "components:ui"
  },
  {
    "name": "typing-animation",
    "files": [
      "ui/typing-animation.tsx"
    ],
    "type": "components:ui"
  },
  {
    "name": "tweet-card",
    "files": [
      "ui/tweet-card.tsx"
    ],
    "type": "components:ui"
  },
  {
    "name": "video-modal",
    "dependencies": [
      "@radix-ui/react-dialog"
    ],
    "files": [
      "ui/video-modal.tsx"
    ],
    "type": "components:ui"
  },
  {
    "name": "wavy-dot-pattern",
    "dependencies": [
      "react-anime"
    ],
    "files": [
      "ui/wavy-dot-pattern.tsx"
    ],
    "type": "components:ui"
  },
  {
    "name": "wavy-text",
    "files": [
      "ui/wavy-text.tsx"
    ],
    "type": "components:ui"
  },
  {
    "name": "word-fade-in",
    "files": [
      "ui/word-fade-in.tsx"
    ],
    "type": "components:ui"
  },
  {
    "name": "word-pull-up",
    "files": [
      "ui/word-pull-up.tsx"
    ],
    "type": "components:ui"
  },
  {
    "name": "word-rotate",
    "files": [
      "ui/word-rotate.tsx"
    ],
    "type": "components:ui"
  },
  {
    "name": "rainbow-button",
    "files": [
      "ui/rainbow-button.tsx"
    ],
    "type": "components:ui"
  }
]
