{
  "name": "tour-demo",
  "type": "registry:example",
  "files": [
    {
      "path": "example/tour-demo.tsx",
      "content": "import * as React from 'react'\n\nimport { Button } from '~/registry/miami/ui/button'\nimport {\n   Card,\n   CardContent,\n   CardDescription,\n   CardFooter,\n   CardHeader,\n   CardTitle,\n} from '~/registry/miami/ui/card'\nimport { Input } from '~/registry/miami/ui/input'\nimport { TourFactory } from '~/registry/miami/ui/tour'\n\nconst tour = TourFactory([\n   'buttonOne',\n   'buttonTwo',\n   'missingButton',\n   'buttonFour',\n   'emailInput',\n])\n\nfunction TourDisplay(props: {\n   children: React.ReactNode\n   title?: string\n   description?: string\n}) {\n   const ctx = tour.useContext()\n   return (\n      <Card className=\"w-[350px]\">\n         <CardHeader>\n            <CardTitle>{props.title}</CardTitle>\n            <CardDescription>{props.description}</CardDescription>\n         </CardHeader>\n         <CardContent>{props.children}</CardContent>\n         <CardFooter>\n            {ctx.current < ctx.nodes.size\n               ? (\n                     <div className=\"flex w-full justify-between\">\n                        <Button variant=\"outline\" onClick={ctx.close}>\n                           Close\n                        </Button>\n                        <div>\n                           <Button onClick={ctx.previous}>Previous</Button>\n                           <Button onClick={ctx.next}>Next</Button>\n                        </div>\n                     </div>\n                  )\n               : (\n                     <div className=\"flex w-full justify-end\">\n                        <Button onClick={ctx.previous}>Previous</Button>\n                        <Button className=\"bg-green-800\" onClick={ctx.close}>\n                           Finish\n                        </Button>\n                     </div>\n                  )}\n         </CardFooter>\n      </Card>\n   )\n}\n\nfunction TourApplication() {\n   const ctx = tour.useContext()\n   return (\n      <div className=\"flex h-96 w-full items-center justify-center\">\n         <div className=\"absolute bottom-2 left-2 flex gap-2\">\n            <tour.TourFocus\n               name=\"buttonOne\"\n               tourRender={(\n                  <TourDisplay title=\"Create Incident\">\n                     <h1>This button creates an incident</h1>\n                     <p>helpful text about this button</p>\n                  </TourDisplay>\n               )}\n            >\n               <Button>Create Incident</Button>\n            </tour.TourFocus>\n            <tour.TourFocus\n               name=\"buttonFour\"\n               tourRender={(\n                  <TourDisplay title=\"Update Incident\">\n                     <h1>This button pushes your updates</h1>\n                     <p>helpful text about this button</p>\n                  </TourDisplay>\n               )}\n            >\n               <Button>Update Incident</Button>\n            </tour.TourFocus>\n         </div>\n         <div className=\"absolute right-2 top-12 flex gap-2\">\n            <tour.TourFocus\n               name=\"buttonTwo\"\n               tourRender={(\n                  <TourDisplay title=\"Resolve Incident\">\n                     <h1>This button Resolves the Incident</h1>\n                     <p>helpful text about this button</p>\n                  </TourDisplay>\n               )}\n            >\n               <Button>Resolve Incident</Button>\n            </tour.TourFocus>\n         </div>\n         <div>\n            <tour.TourFocus\n               name=\"emailInput\"\n               tourRender={(\n                  <TourDisplay title=\"Email Input\">\n                     <h1>This is where you put incident info</h1>\n                     <p>helpful text about this input</p>\n                  </TourDisplay>\n               )}\n            >\n               <Input type=\"email\" placeholder=\"Email\" />\n            </tour.TourFocus>\n         </div>\n         <div className=\"absolute bottom-2 right-2\">\n            <Button onClick={ctx.open}>Open Tour</Button>\n         </div>\n      </div>\n   )\n}\n\nexport default function TourDemo() {\n   return (\n      <tour.TourProvider>\n         <TourApplication />\n      </tour.TourProvider>\n   )\n}\n",
      "type": "registry:component",
      "target": ""
    }
  ]
}
